[{"name":"Care One Hemorrhoidal","price":932.18},{"name":"SNORING HP","price":53.59},{"name":"ROPINIROLE HYDROCHLORIDE","price":266.44},{"name":"kirkland signature minoxidil","price":49.17},{"name":"Agaricus Equisetum Special Order","price":585.93},{"name":"Lamotrigine Extended Release","price":245.63},{"name":"CLARINS Ever Matte SPF 15 - 105 Nude","price":696.06},{"name":"Childrens Allegra Allergy","price":650.97},{"name":"PredniSONE","price":286.43},{"name":"Spironolactone","price":933.69},{"name":"U-max Multi BB","price":137.16},{"name":"Phenylephrine HCl","price":459.89},{"name":"Finasteride","price":1374.01},{"name":"Clarins Paris Skin Illusion - 114 cappuccino","price":811.42},{"name":"Enalapril Maleate","price":72.71},{"name":"MEDICATED DANDRUFF","price":1351.02},{"name":"Pleo Lat","price":720.08},{"name":"Myristica Argentum Sinus Relief","price":904.52},{"name":"Glyburide","price":95.1},{"name":"Burn Jel","price":209.57},{"name":"CHAMOMILLA","price":37.97},{"name":"NEO-POLY-BAC HYDRO","price":967.32},{"name":"Prednisone","price":550.72},{"name":"Isosorbide Mononitrate","price":789.91},{"name":"Glipizide and Metformin Hydrochloride","price":953.6},{"name":"TERSI","price":554.91},{"name":"SEPHORA Acne-Fighting Mattifying Moisturizer","price":1019.28},{"name":"Smooth texture Orange flavor","price":976.65},{"name":"DAYWEAR PLUS MULTI PROTECTION TINTED MOISTURIZER","price":555.12},{"name":"Zonisamide","price":1305.41},{"name":"Peter Island Continous sunscreen kids","price":471.3},{"name":"GOONG SECRET CALMING BATH","price":742.47},{"name":"Clearskin","price":968.59},{"name":"No7 Protect and Perfect Foundation Sunscreen Broad Spectrum SPF 15 Cool Ivory","price":616.19},{"name":"Alcohol Free Antiseptic","price":1486.07},{"name":"smart sense nighttime cold and flu relief","price":1101.77},{"name":"Warfarin Sodium","price":1379.79},{"name":"Oxygen","price":1242.92}]